retroplanner/__init__.py
retroplanner/main.py
retroplanner/template/day.tex
retroplanner/template/latex_general/footer.tex
retroplanner/template/latex_general/header.tex
retroplanner/template/latex_general/main.tex
retroplanner/template/latex_general/tikz.tex
retroplanner/template/tikz/conf.tex
retroplanner/template/tikz/conf.texbck
retroplanner/template/tikz/day.tex
retroplanner/template/tikz/deadline.tex
retroplanner/template/tikz/deadline_mixte.tex
retroplanner/template/tikz/formation.tex
retroplanner/template/tikz/formation_bck.tex
retroplanner/template/tikz/holiday.tex
retroplanner/template/tikz/holiday.texbck
retroplanner/template/tikz/redaction.tex
retroplanner-0.0.2.dist-info/METADATA
retroplanner-0.0.2.dist-info/WHEEL
retroplanner-0.0.2.dist-info/licenses/LICENCE
retroplanner-0.0.2.dist-info/RECORD
